django_flavour
