Metadata-Version: 1.0
Name: django-flavour
Version: 0.0.6
Summary: Adds flavour support for other django addons
Home-page: https://www.divio.com
Author: Divio AG
Author-email: info@divio.ch
License: UNKNOWN
Platform: UNKNOWN
